nfc_module/__init__.py
nfc_module/nfc.py
nfc_module/nfc_module.py
nfc_module-1.dist-info/METADATA
nfc_module-1.dist-info/WHEEL
nfc_module-1.dist-info/top_level.txt
nfc_module-1.dist-info/RECORD
