Metadata-Version: 2.1
Name: nfc-module
Version: 1
Summary: NFC读写操作
Home-page: https://www.github.com/cpak00/nfc_module
Author: cpak00
Author-email: cymcpak00@gmail.com
Maintainer: cpak00
Maintainer-email: cymcpak00@gmail.com
License: MIT License
Platform: all
Classifier: Development Status :: 4 - Beta
Classifier: Operating System :: OS Independent
Classifier: Intended Audience :: Developers
Classifier: License :: OSI Approved :: BSD License
Classifier: Programming Language :: Python :: 3
Classifier: Programming Language :: Python :: 3.4
Classifier: Programming Language :: Python :: 3.5
Classifier: Programming Language :: Python :: 3.6
Classifier: Programming Language :: Python :: 3.7
Classifier: Topic :: Software Development :: Libraries
Requires-Dist: pyserial (==3.4)
